wpconfigr/__init__.py
wpconfigr/__main__.py
wpconfigr/wp_config_file.py
wpconfigr/wp_config_string.py
wpconfigger-1.0.0.dist-info/LICENSE
wpconfigger-1.0.0.dist-info/METADATA
wpconfigger-1.0.0.dist-info/WHEEL
wpconfigger-1.0.0.dist-info/top_level.txt
wpconfigger-1.0.0.dist-info/RECORD
