Metadata-Version: 2.1
Name: wpconfigger
Version: 1.0.0
Summary: Read and write configuration values in a WordPress "wp-config.php" file.
Home-page: https://github.com/cariad/py-wpconfigr
Author: Cariad Eccleston
Author-email: cariad@cariad.me
License: MIT
Classifier: Development Status :: 5 - Production/Stable
Classifier: Environment :: Console
Classifier: Intended Audience :: Developers
Classifier: License :: OSI Approved :: MIT License
Classifier: Natural Language :: English
Classifier: Programming Language :: Python :: 3
Classifier: Operating System :: OS Independent
Classifier: Topic :: Internet :: WWW/HTTP :: Site Management
License-File: LICENSE
Provides-Extra: dev
Requires-Dist: autopep8 ; extra == 'dev'
Requires-Dist: coverage ; extra == 'dev'
Requires-Dist: pylint ; extra == 'dev'
